litecointx/__init__.py
litecointx/version.py
litecointx/wallet.py
litecointx/core/__init__.py
litecointx/core/script.py
litecointx/tests/__init__.py
litecointx/tests/test_wallet.py
python_litecointx-0.1.2.dist-info/LICENSE
python_litecointx-0.1.2.dist-info/METADATA
python_litecointx-0.1.2.dist-info/WHEEL
python_litecointx-0.1.2.dist-info/top_level.txt
python_litecointx-0.1.2.dist-info/RECORD
