Metadata-Version: 2.1
Name: python-litecointx
Version: 0.1.2
Summary: Litecoin module for use with python-bitcointx
Home-page: https://github.com/Simplexum/python-litecointx
License: UNKNOWN
Keywords: litecoin
Platform: UNKNOWN
Classifier: Programming Language :: Python :: 3.6
Classifier: Programming Language :: Python :: 3.7
Classifier: Programming Language :: Python :: 3.8
Classifier: License :: OSI Approved :: GNU Lesser General Public License v3 or later (LGPLv3+)
Requires-Python: >=3.6
Requires-Dist: python-bitcointx (<2,>=1.0.0)
